README.md
setup.py
chargrid/__init__.py
chargrid/__main__.py
chargrid/_chargrid.py
chargrid/factory_test.py
chargrid/meta.py
chargrid.egg-info/PKG-INFO
chargrid.egg-info/SOURCES.txt
chargrid.egg-info/dependency_links.txt
chargrid.egg-info/requires.txt
chargrid.egg-info/top_level.txt
chargrid/enemy/__init__.py
chargrid/enemy/_enemy.py